discovery/__init__.py
discovery/data_matching/__init__.py
discovery/data_matching/data_match_interface.py
discovery/data_matching/dataframe_matcher.py
discovery/data_matching/matching_methods/__init__.py
discovery/data_matching/matching_methods/match_column_name_lcs.py
discovery/data_matching/matching_methods/match_column_name_levenshtein.py
discovery/data_matching/matching_methods/match_column_name_wordnet.py
discovery/data_matching/matching_methods/match_data_dynamic_time_warping.py
discovery/data_matching/matching_methods/match_data_pearson_coefficient.py
discovery/data_matching/matching_methods/match_data_two_sample_t_test.py
discovery/data_matching/matching_methods/match_identical_column_names.py
discovery/data_matching/matching_methods/match_identical_rows.py
discovery/discovery_client.py
discovery/launch_config.yaml
discovery/logging_conf.yaml
discovery/metadata/__init__.py
discovery/metadata/catalogue_item.py
discovery/metadata/catalogue_item_builders.py
discovery/metadata/catalogue_metadata.py
discovery/metadata/schema.json
discovery/utils/__init__.py
discovery/utils/custom_exceptions.py
discovery/utils/data_handling/__init__.py
discovery/utils/data_handling/catalogue_data.py
discovery/utils/data_handling/data_size.py
discovery/utils/data_handling/local_csv_handler.py
discovery/utils/datagen.py
discovery/utils/decorators/__init__.py
discovery/utils/decorators/persist_execution.py
discovery/utils/decorators/type_enforcer.py
discovery/utils/visualizer.py
DataCatalogueSystem-1.0.1.dist-info/WHEEL
DataCatalogueSystem-1.0.1.dist-info/METADATA
DataCatalogueSystem-1.0.1.dist-info/licenses/LICENSE
DataCatalogueSystem-1.0.1.dist-info/RECORD
