Metadata-Version: 2.1
Name: DataCatalogueSystem
Version: 1.0.1
Summary: This library is used to discover and assign metadata to large unrefined data sets
License: MIT
Author-email: MII <mnel.jnr@gmail.com>
Requires-Python: >=3.10
Requires-Dist: dtaidistance>=2.3.10
Requires-Dist: faker>=16.6.0
Requires-Dist: flake8>=5.0.4
Requires-Dist: graphviz>=0.20.1
Requires-Dist: jsonschema>=4.17.3
Requires-Dist: kaggle>=1.5.12
Requires-Dist: levenshtein>=0.20.7
Requires-Dist: nltk>=3.7
Requires-Dist: pandas>=1.5.0
Requires-Dist: plotly>=5.10.0
Requires-Dist: pyaml>=21.10.1
Requires-Dist: pytest>=7.1.3
Requires-Dist: setuptools>=65.5.0
Requires-Dist: statsmodels>=0.13.2
